kart/__init__.py
kart/ext/asciidoc.py
kart/ext/documentation.py
kart/ext/markdown.py
kart/ext/toml.py
kart/js/hot_reload.js
kart/mappers.py
kart/miners.py
kart/modifiers.py
kart/renderers.py
kart/utils.py
kart-0.16.1.dist-info/LICENSE
kart-0.16.1.dist-info/METADATA
kart-0.16.1.dist-info/WHEEL
kart-0.16.1.dist-info/RECORD
