Metadata-Version: 2.1
Name: Kart
Version: 0.16.1
Summary: A very flexible static site generator written in python
License: MIT
Author: Giacomo Caironi
Author-email: giacomo.caironi@gmail.com
Requires-Python: >=3.9,<4.0
Classifier: License :: OSI Approved :: MIT License
Classifier: Programming Language :: Python :: 3
Classifier: Programming Language :: Python :: 3.9
Classifier: Programming Language :: Python :: 3.10
Classifier: Programming Language :: Python :: 3.11
Classifier: Programming Language :: Python :: 3.12
Classifier: Programming Language :: Python :: 3.13
Provides-Extra: toml
Requires-Dist: aiohttp (>=3.9.3,<4.0.0)
Requires-Dist: jinja2 (>=3.1,<3.2)
Requires-Dist: mistune (>=3.0,<4.0)
Requires-Dist: pygments (>=2.6.1,<3.0.0)
Requires-Dist: python-dateutil (>=2.8.2,<3.0.0)
Requires-Dist: python-slugify (>=8.0,<9.0)
Requires-Dist: pyyaml (>=6.0,<7.0)
Requires-Dist: tomli (>=2.0.1,<3.0.0) ; extra == "toml"
Requires-Dist: watchfiles (>=0.24.0,<0.25.0)
